textblaze_to_espanso/__init__.py
textblaze_to_espanso/__main__.py
textblaze_to_espanso/converter.py
textblaze_to_espanso/settings.py
textblaze_to_espanso-0.1.10.dist-info/METADATA
textblaze_to_espanso-0.1.10.dist-info/WHEEL
textblaze_to_espanso-0.1.10.dist-info/top_level.txt
textblaze_to_espanso-0.1.10.dist-info/RECORD
